DisOAuth/__init__.py
DisOAuth/__version__.py
DisOAuth/common.py
DisOAuth/url.py
DisOAuth-0.2.0.dist-info/LICENSE
DisOAuth-0.2.0.dist-info/METADATA
DisOAuth-0.2.0.dist-info/WHEEL
DisOAuth-0.2.0.dist-info/top_level.txt
DisOAuth-0.2.0.dist-info/RECORD
