Metadata-Version: 2.1
Name: DisOAuth
Version: 0.2.0
Summary: Helps with discord oauth2
Project-URL: Homepage, https://github.com/Arcader717/DiscordOAuth2
Project-URL: Bug Tracker, https://github.com/Arcader717/DiscordOAuth2/issues
Project-URL: Repository, https://github.com/Arcader717/DiscordOAuth2
Requires-Python: >=3.7
License-File: LICENSE
Requires-Dist: requests
